setup.py
exercicios/__init__.py
exercicios/buscador.py
pypraticot6/__init__.py
pypraticot6/github.py
pypraticot6.egg-info/PKG-INFO
pypraticot6.egg-info/SOURCES.txt
pypraticot6.egg-info/dependency_links.txt
pypraticot6.egg-info/not-zip-safe
pypraticot6.egg-info/requires.txt
pypraticot6.egg-info/top_level.txt