Metadata-Version: 1.1
Name: pypraticot6
Version: 0.1
Summary: Pacote de exemplo do curso pypratico
Home-page: https://github.com/renzon/pypratico
Author: Renzo Nuccitelli
Author-email: renzo.n@gmail.com
License: AGPL
Platform: UNKNOWN
Classifier: Development Status :: 4 - Beta
Classifier: Environment :: Web Environment
Classifier: Intended Audience :: Developers
Classifier: License :: OSI Approved :: GNU Affero General Public License v3 or later (AGPLv3+)
Classifier: Operating System :: OS Independent
Classifier: Programming Language :: Python
Classifier: Framework :: Paste
